LICENSE
MANIFEST.in
README.md
setup.py
article/__init__.py
article/cms_plugins.py
article/models.py
article/migrations/0001_initial.py
article/migrations/0002_auto__chg_field_article_body.py
article/migrations/__init__.py
article/templates/article/plugin.html
django_theherk_article.egg-info/PKG-INFO
django_theherk_article.egg-info/SOURCES.txt
django_theherk_article.egg-info/dependency_links.txt
django_theherk_article.egg-info/top_level.txt